LICENSE.txt
MANIFEST.in
README.rst
setup.cfg
setup.py
versioneer.py
sql_to_ibis/__init__.py
sql_to_ibis/_version.py
sql_to_ibis/query_info.py
sql_to_ibis/sql_select_query.py
sql_to_ibis.egg-info/PKG-INFO
sql_to_ibis.egg-info/SOURCES.txt
sql_to_ibis.egg-info/dependency_links.txt
sql_to_ibis.egg-info/requires.txt
sql_to_ibis.egg-info/top_level.txt
sql_to_ibis/conversions/__init__.py
sql_to_ibis/conversions/conversions.py
sql_to_ibis/exceptions/__init__.py
sql_to_ibis/exceptions/sql_exception.py
sql_to_ibis/grammar/__init__.py
sql_to_ibis/grammar/sql.lark
sql_to_ibis/parsing/__init__.py
sql_to_ibis/parsing/aggregation_aliases.py
sql_to_ibis/parsing/sql_parser.py
sql_to_ibis/parsing/transformers.py
sql_to_ibis/sql/__init__.py
sql_to_ibis/sql/column_utils.py
sql_to_ibis/sql/sql_clause_objects.py
sql_to_ibis/sql/sql_objects.py
sql_to_ibis/sql/sql_value_objects.py
sql_to_ibis/tests/__init__.py
sql_to_ibis/tests/conftest.py
sql_to_ibis/tests/markers.py
sql_to_ibis/tests/test_errors.py
sql_to_ibis/tests/test_expression_execution.py
sql_to_ibis/tests/test_object_representations.py
sql_to_ibis/tests/test_tables.py
sql_to_ibis/tests/utils.py